shiivalibrary/__init__.py
shiivalibrary/main.py
shiivalibrary-1.2.0.dist-info/METADATA
shiivalibrary-1.2.0.dist-info/WHEEL
shiivalibrary-1.2.0.dist-info/top_level.txt
shiivalibrary-1.2.0.dist-info/RECORD
